candela_kit/__init__.py
candela_kit/_api/__init__.py
candela_kit/_api/api_client.py
candela_kit/_api/client.py
candela_kit/_api/websocket_client.py
candela_kit/app.py
candela_kit/cli/__init__.py
candela_kit/cli/actions/__init__.py
candela_kit/cli/actions/chat_action.py
candela_kit/cli/actions/config_action.py
candela_kit/cli/actions/delete_action.py
candela_kit/cli/actions/list_action.py
candela_kit/cli/actions/show_action.py
candela_kit/cli/app.py
candela_kit/common/__init__.py
candela_kit/common/common.py
candela_kit/common/spinner.py
candela_kit/directive.py
candela_kit/dtos/__init__.py
candela_kit/dtos/apps.py
candela_kit/dtos/circuits.py
candela_kit/dtos/common.py
candela_kit/dtos/directives.py
candela_kit/dtos/models.py
candela_kit/dtos/sessions.py
candela_kit/dtos/tools.py
candela_kit/dtos/traces.py
candela_kit/dtos/translator.py
candela_kit/event.py
candela_kit/exceptions.py
candela_kit/ignite/__init__.py
candela_kit/ignite/circuits.py
candela_kit/ignite/intent.py
candela_kit/ignite/states.py
candela_kit/profiles.py
candela_kit/sessions/__init__.py
candela_kit/sessions/contexts.py
candela_kit/sessions/manager.py
candela_kit/tools/__init__.py
candela_kit/tools/base.py
candela_kit/tools/builtin/__init__.py
candela_kit/tools/builtin/lumi/__init__.py
candela_kit/tools/builtin/lumi/lumi_providers.py
candela_kit/tools/builtin/lumi/run_sql.py
candela_kit/tools/builtin/lumi/utils.py
candela_kit/tools/builtin/lusid/__init__.py
candela_kit/tools/builtin/lusid/common.py
candela_kit/tools/builtin/lusid/create_equity.py
candela_kit/tools/builtin/lusid/create_fx_fwd.py
candela_kit/tools/builtin/lusid/create_portfolio.py
candela_kit/tools/builtin/lusid/create_transaction.py
candela_kit/tools/tool_extract.py
candela_kit-0.2.16.dist-info/METADATA
candela_kit-0.2.16.dist-info/WHEEL
candela_kit-0.2.16.dist-info/entry_points.txt
candela_kit-0.2.16.dist-info/RECORD
