Metadata-Version: 2.3
Name: candela-kit
Version: 0.2.16
Summary: Client library for Candela
Author: Candela Team
Author-email: engineering@finbourne.com
Requires-Python: >=3.11,<4.0
Classifier: Programming Language :: Python :: 3
Classifier: Programming Language :: Python :: 3.11
Classifier: Programming Language :: Python :: 3.12
Classifier: Programming Language :: Python :: 3.13
Requires-Dist: aiofiles (>=24.1.0,<25.0.0)
Requires-Dist: black (>=25.1.0,<26.0.0)
Requires-Dist: boto3 (>=1.35.35,<2.0.0)
Requires-Dist: cryptography (>=42.0.5,<42.1.0)
Requires-Dist: graphviz (>=0.20.3,<0.21.0)
Requires-Dist: lumipy (>=1.0.254,<2.0.0)
Requires-Dist: lusid-sdk (>=2.1.423,<3.0.0)
Requires-Dist: notebook (>=7.3.3,<8.0.0)
Requires-Dist: pandas (>=2.2.3,<3.0.0)
Requires-Dist: pydantic (>=2.9.2,<3.0.0)
Requires-Dist: pyfiglet (>=1.0.2,<2.0.0)
Requires-Dist: pygments (>=2.19.1,<3.0.0)
Requires-Dist: python-dotenv (>=1.1.0,<2.0.0)
Requires-Dist: pyyaml (>=6.0.2,<7.0.0)
Requires-Dist: tabulate (>=0.9.0,<0.10.0)
Requires-Dist: websockets (>=15.0.1,<16.0.0)
